[
  {
    "ID do pedido": "2507011VJTCJ76",
    "Status do pedido": "Concluído",
    "Cancelar Motivo": "",
    "Status da Devolução / Reembolso": "",
    "Número de rastreamento": "BR257245178326Y",
    "Opção de envio": "Shopee Xpress",
    "Método de envio": "Postagem",
    "Data prevista de envio": "2025-07-01 23:59",
    "Tempo de Envio": "2025-07-01 16:06",
    "Data de criação do pedido": "2025-07-01 07:30",
    "Hora do pagamento do pedido": "2025-07-01 07:32",
    "Nº de referência do SKU principal": "",
    "Nome do Produto": "Tênis Esportivo Unissex Masculino Feminino Academia Corrida Acessível Lançamento - Envio Rápido",
    "Número de referência SKU": "",
    "Nome da variação": "PRETO PRETO,43",
    "Preço original": 69.9,
    "Preço acordado": 46.78,
    "Quantidade": 1,
    "Returned quantity": 0,
    "Subtotal do produto": 46.78,
    "Desconto do vendedor": 23.12,
    "Desconto do vendedor__1": 23.12,
    "Reembolso Shopee": 0,
    "Peso total SKU": 0.6,
    "Número de produtos pedidos": 1,
    "Peso total do pedido": 0.6,
    "Código do Cupom": "ZUNNLOJA1",
    "Cupom do vendedor": 0.5,
    "Seller Absorbed Coin Cashback": 0,
    "Cupom Shopee": 0,
    "Indicador da Leve Mais por Menos": "N",
    "Desconto Shopee da Leve Mais por Menos": 0,
    "Desconto da Leve Mais por Menos do vendedor": 0,
    "Compensar Moedas Shopee": 3,
    "Total descontado Cartão de Crédito": 0,
    "Valor Total": 58.82,
    "Taxa de envio pagas pelo comprador": 12.04,
    "Desconto de Frete Aproximado": 0,
    "Taxa de Envio Reversa": 0,
    "Taxa de transação": 0,
    "Taxa de comissão": 8.56,
    "Taxa de serviço": 4.69,
    "Total global": 58.29,
    "Valor estimado do frete": 12.04,
    "Nome de usuário (comprador)": "eliasmarcos227",
    "Nome do destinatário": "E******o",
    "Telefone": "******16",
    "CPF do Comprador": "",
    "Endereço de entrega": "Ru******",
    "Cidade": "",
    "Bairro": "Redentor",
    "Cidade__1": "Caconde",
    "UF": "São Paulo",
    "País": "BR",
    "CEP": 13770959,
    "Observação do comprador": "",
    "Hora completa do pedido": "2025-07-08 11:29",
    "Nota": ""
  },
  {
    "ID do pedido": "2507012VJTCJ77",
    "Status do pedido": "Concluído",
    "Cancelar Motivo": "",
    "Status da Devolução / Reembolso": "",
    "Número de rastreamento": "BR257245178327Z",
    "Opção de envio": "Shopee Xpress",
    "Método de envio": "Postagem",
    "Data prevista de envio": "2025-07-02 23:59",
    "Tempo de Envio": "2025-07-02 16:06",
    "Data de criação do pedido": "2025-07-02 08:15",
    "Hora do pagamento do pedido": "2025-07-02 08:17",
    "Nº de referência do SKU principal": "",
    "Nome do Produto": "Camiseta Básica Masculina 100% Algodão",
    "Número de referência SKU": "",
    "Nome da variação": "AZUL,M",
    "Preço original": 29.9,
    "Preço acordado": 19.9,
    "Quantidade": 2,
    "Returned quantity": 0,
    "Subtotal do produto": 39.8,
    "Desconto do vendedor": 10.0,
    "Desconto do vendedor__1": 10.0,
    "Reembolso Shopee": 0,
    "Peso total SKU": 0.3,
    "Número de produtos pedidos": 2,
    "Peso total do pedido": 0.3,
    "Código do Cupom": "",
    "Cupom do vendedor": 0,
    "Seller Absorbed Coin Cashback": 0,
    "Cupom Shopee": 0,
    "Indicador da Leve Mais por Menos": "N",
    "Desconto Shopee da Leve Mais por Menos": 0,
    "Desconto da Leve Mais por Menos do vendedor": 0,
    "Compensar Moedas Shopee": 0,
    "Total descontado Cartão de Crédito": 0,
    "Valor Total": 39.8,
    "Taxa de envio pagas pelo comprador": 8.0,
    "Desconto de Frete Aproximado": 0,
    "Taxa de Envio Reversa": 0,
    "Taxa de transação": 0,
    "Taxa de comissão": 5.97,
    "Taxa de serviço": 2.39,
    "Total global": 39.8,
    "Valor estimado do frete": 8.0,
    "Nome de usuário (comprador)": "maria123",
    "Nome do destinatário": "M******a",
    "Telefone": "******45",
    "CPF do Comprador": "",
    "Endereço de entrega": "Av******",
    "Cidade": "",
    "Bairro": "Centro",
    "Cidade__1": "São Paulo",
    "UF": "São Paulo",
    "País": "BR",
    "CEP": 01000000,
    "Observação do comprador": "",
    "Hora completa do pedido": "2025-07-02 14:30",
    "Nota": ""
  },
  {
    "ID do pedido": "2507013VJTCJ78",
    "Status do pedido": "Em trânsito",
    "Cancelar Motivo": "",
    "Status da Devolução / Reembolso": "",
    "Número de rastreamento": "BR257245178328A",
    "Opção de envio": "Shopee Xpress",
    "Método de envio": "Postagem",
    "Data prevista de envio": "2025-07-03 23:59",
    "Tempo de Envio": "2025-07-03 10:30",
    "Data de criação do pedido": "2025-07-03 09:45",
    "Hora do pagamento do pedido": "2025-07-03 09:47",
    "Nº de referência do SKU principal": "",
    "Nome do Produto": "Bolsa Feminina Couro Sintético",
    "Número de referência SKU": "",
    "Nome da variação": "PRETA",
    "Preço original": 89.9,
    "Preço acordado": 59.9,
    "Quantidade": 1,
    "Returned quantity": 0,
    "Subtotal do produto": 59.9,
    "Desconto do vendedor": 30.0,
    "Desconto do vendedor__1": 30.0,
    "Reembolso Shopee": 0,
    "Peso total SKU": 0.8,
    "Número de produtos pedidos": 1,
    "Peso total do pedido": 0.8,
    "Código do Cupom": "DESCONTO10",
    "Cupom do vendedor": 5.0,
    "Seller Absorbed Coin Cashback": 0,
    "Cupom Shopee": 0,
    "Indicador da Leve Mais por Menos": "N",
    "Desconto Shopee da Leve Mais por Menos": 0,
    "Desconto da Leve Mais por Menos do vendedor": 0,
    "Compensar Moedas Shopee": 2,
    "Total descontado Cartão de Crédito": 0,
    "Valor Total": 54.9,
    "Taxa de envio pagas pelo comprador": 10.0,
    "Desconto de Frete Aproximado": 0,
    "Taxa de Envio Reversa": 0,
    "Taxa de transação": 0,
    "Taxa de comissão": 8.24,
    "Taxa de serviço": 3.85,
    "Total global": 54.9,
    "Valor estimado do frete": 10.0,
    "Nome de usuário (comprador)": "ana456",
    "Nome do destinatário": "A******a",
    "Telefone": "******78",
    "CPF do Comprador": "",
    "Endereço de entrega": "Rua******",
    "Cidade": "",
    "Bairro": "Copacabana",
    "Cidade__1": "Rio de Janeiro",
    "UF": "Rio de Janeiro",
    "País": "BR",
    "CEP": 22000000,
    "Observação do comprador": "",
    "Hora completa do pedido": "2025-07-03 16:20",
    "Nota": ""
  }
]
